efmpv/__init__.py
efmpv/efmpv.py
puddler/__init__.py
puddler/mediaserver_information.py
puddler/playback_reporting.py
puddler/playing.py
puddler/puddler.py
Puddler-0.2.dev4.dist-info/COPYING
Puddler-0.2.dev4.dist-info/METADATA
Puddler-0.2.dev4.dist-info/WHEEL
Puddler-0.2.dev4.dist-info/top_level.txt
Puddler-0.2.dev4.dist-info/RECORD
