Metadata-Version: 2.1
Name: Puddler
Version: 0.2.dev4
Summary: Emby/Jellyfin command line client, powered by mpv.
Home-page: https://github.com/Vernoxvernax/Puddler
Author: VernoxVernax
Author-email: vernoxvernax@gmail.com
License: GNU General Public License v3.0
Platform: UNKNOWN
License-File: COPYING
Requires-Dist: python-mpv
Requires-Dist: python-mpv-jsonipc
Requires-Dist: requests
Requires-Dist: appdirs
Requires-Dist: getch
